{"name":"queue","slug":"queue","count":1,"postlist":[{"title":"「1014」Waiting in Line","uid":"be23bf1b6bcf5e89051d9bbdaa72f245","slug":"1014-Waiting-in-Line","date":"2022-03-15T03:27:08.000Z","updated":"2022-03-15T10:01:02.285Z","comments":true,"path":"api/articles/1014-Waiting-in-Line.json","keywords":null,"cover":null,"text":"➳ENTRY $\\qquad$Suppose a bank has $N$ windows open for service. There is a yellow line in front of the windows which devides the waiting are...","link":"","photos":[],"count_time":{"symbolsCount":"5.2k","symbolsTime":"5 mins."},"categories":[{"name":"PAT（Advanced Level）Practice","slug":"PAT（Advanced-Level）Practice","count":153,"path":"api/categories/PAT（Advanced-Level）Practice.json"}],"tags":[{"name":"C＋＋","slug":"C＋＋","count":160,"path":"api/tags/C＋＋.json"},{"name":"queue","slug":"queue","count":1,"path":"api/tags/queue.json"}],"author":{"name":"Starlit Rover","slug":"blog-author","avatar":"https://encrypted-tbn3.gstatic.com/images?q=tbn:ANd9GcQWu4nWh5NV26rlAS5lR23iaundn5IVlV3EpYGNAdtnMObooQnk","link":"/","description":"Stroll in the starlit firmament~","socials":{"github":"https://github.com/StarlitRover","twitter":"https://twitter.com/Starlit_Rover","stackoverflow":"","wechat":"","qq":"","weibo":"","zhihu":"","csdn":"","juejin":"","customs":{"steam":{"icon":"/images/aurora/steam.svg","link":"https://steamcommunity.com/id/starlitrover/"}}}}}]}